{
  "generated_at": "2026-06-12T07:41:33.511719+00:00",
  "launchd": {
    "plist_exists": true,
    "loaded": true,
    "last_status": "ok",
    "last_log_at": "2026-06-12 15:15:36",
    "error_hint": null
  },
  "data_freshness": {
    "data_items": {
      "exists": true,
      "mtime": "2026-06-12T07:40:59.498531+00:00",
      "age_minutes": 0.6,
      "size_kb": 510.0
    },
    "data_status": {
      "exists": true,
      "mtime": "2026-06-12T07:40:59.535676+00:00",
      "age_minutes": 0.6,
      "size_kb": 24.3
    },
    "data_local_items": {
      "exists": true,
      "mtime": "2026-06-12T07:41:33.338144+00:00",
      "age_minutes": 0.0,
      "size_kb": 2956.4
    },
    "data_local_status": {
      "exists": true,
      "mtime": "2026-06-12T04:10:37.707076+00:00",
      "age_minutes": 210.9,
      "size_kb": 24.2
    }
  },
  "credentials_files": {
    "getnote_env": {
      "exists": true,
      "mtime": "2026-06-11T03:57:20.804411+00:00"
    }
  },
  "github_actions": {
    "last_cloud_refresh": "2026-06-12T12:39:54+08:00",
    "hours_ago": 3.0
  }
}